py_manager_api/__init__.py
py_manager_api_test-0.0.2.dist-info/LICENSE
py_manager_api_test-0.0.2.dist-info/METADATA
py_manager_api_test-0.0.2.dist-info/WHEEL
py_manager_api_test-0.0.2.dist-info/top_level.txt
py_manager_api_test-0.0.2.dist-info/RECORD
