Metadata-Version: 2.1
Name: py-manager-api-test
Version: 0.0.2
Summary: BFJ manager api for python user
Home-page: https://github.com/pypa/sampleproject
Author: BFJ
Author-email: wuyou1020@hotmail.com
License: UNKNOWN
Platform: UNKNOWN
Classifier: Programming Language :: Python :: 3
Classifier: License :: OSI Approved :: MIT License
Classifier: Operating System :: OS Independent
